[
  {
    "id": 11,
    "name": "Main School Building",
    "shape": "rect",
    "x": -1347,
    "y": -849,
    "rotation": -3,
    "width": 389,
    "length": 738,
    "clip": 50,
    "on_enter": [
      {
        "show_dialog": {
          "type": "change_map",
          "map": 2,
          "description": "Do you want to enter the main building?"
        }
      }
    ]
  },
  {
    "id": 12,
    "name": "Pool",
    "shape": "rect",
    "x": -2095,
    "y": -1254,
    "rotation": 90,
    "width": 759,
    "length": 202,
    "clip": 50,
    "on_enter": [
      {
        "show_dialog": {
          "type": "change_map",
          "map": 3,
          "description": "Do you want to enter the Pool building?"
        }
      }
    ]
  },
  {
    "id": 13,
    "name": "Rugby Pitch",
    "shape": "rect",
    "x": -1983,
    "y": -370,
    "rotation": 0,
    "width": 408,
    "length": 1006,
    "clip": -1,
    "on_enter": [
      {
        "emote": "rugby"
      }
    ],
    "on_exit": [
      {
        "clear_emote": true
      }
    ]
  },
  {
    "id": 19,
    "shape": "rect",
    "x": -1171,
    "y": -223,
    "width": 413,
    "length": 269,
    "name": "Spawn Area",
    "clip": -1,
    "rotation": -3
  },
  {
    "id": 20,
    "shape": "rect",
    "x": 661,
    "y": 133,
    "width": 1220,
    "length": 39,
    "rotation": 177
  },
  {
    "id": 21,
    "shape": "rect",
    "x": -957,
    "y": -829,
    "name": "Main School Building",
    "rotation": -3,
    "width": 297,
    "length": 686,
    "clip": 40,
    "on_enter": 11
  },
  {
    "id": 22,
    "shape": "rect",
    "x": -224,
    "y": 32,
    "name": "Main School Building",
    "rotation": -1,
    "width": 434,
    "length": 294,
    "clip": 50,
    "on_enter": 11
  },
  {
    "id": 23,
    "shape": "rect",
    "x": -395,
    "y": -968,
    "name": "Main School Building",
    "rotation": -3,
    "width": 711,
    "length": 302,
    "clip": 50,
    "on_enter": 11
  },
  {
    "id": 24,
    "shape": "rect",
    "x": -594,
    "y": -1343,
    "name": "Main School Building",
    "rotation": -3,
    "width": 499,
    "length": 315,
    "clip": 50,
    "on_enter": 11
  },
  {
    "id": 25,
    "shape": "rect",
    "x": -1050,
    "y": -1330,
    "name": "Main School Building",
    "rotation": -4,
    "width": 124,
    "length": 272,
    "clip": 50,
    "on_enter": 11
  },
  {
    "id": 26,
    "shape": "rect",
    "x": -766,
    "y": -837,
    "name": "Main School Building",
    "rotation": -3,
    "width": 116,
    "length": 526,
    "clip": 50,
    "on_enter": 11
  },
  {
    "id": 27,
    "shape": "rect",
    "x": -136,
    "y": -1349,
    "name": "Main School Building",
    "rotation": -2,
    "width": 165,
    "length": 300,
    "clip": 50,
    "on_enter": 11
  },
  {
    "id": 28,
    "shape": "rect",
    "x": 476,
    "y": -409,
    "name": "Main School Building",
    "rotation": -1,
    "width": 254,
    "length": 499,
    "clip": 50,
    "on_enter": 11
  },
  {
    "id": 29,
    "shape": "rect",
    "x": 629,
    "y": -223,
    "name": "Main School Building",
    "rotation": -1,
    "width": 156,
    "length": 95,
    "clip": 50,
    "on_enter": 11
  },
  {
    "id": 30,
    "shape": "rect",
    "x": 108,
    "y": -1091,
    "name": "Main School Building",
    "rotation": -1,
    "width": 484,
    "length": 485,
    "clip": 50,
    "on_enter": 11
  },
  {
    "id": 31,
    "shape": "rect",
    "x": 419,
    "y": -1011,
    "name": "Main School Building",
    "rotation": -1,
    "width": 174,
    "length": 712,
    "clip": 50,
    "on_enter": 11
  },
  {
    "id": 32,
    "shape": "rect",
    "x": 199,
    "y": -706,
    "name": "Main School Building",
    "rotation": -2,
    "width": 305,
    "length": 311,
    "clip": 50,
    "on_enter": 11
  },
  {
    "id": 33,
    "shape": "rect",
    "x": -294,
    "y": -560,
    "name": "Main School Building",
    "rotation": -2,
    "width": 375,
    "length": 790,
    "clip": 50,
    "on_enter": 11
  },
  {
    "id": 34,
    "shape": "rect",
    "x": 728,
    "y": -875,
    "name": "Main School Building",
    "rotation": -3,
    "width": 482,
    "length": 568,
    "clip": 50,
    "on_enter": 11
  },
  {
    "id": 35,
    "shape": "rect",
    "x": -26,
    "y": -803,
    "name": "Main School Building",
    "rotation": -1,
    "width": 375,
    "length": 211,
    "clip": 50,
    "on_enter": 11
  },
  {
    "id": 36,
    "shape": "rect",
    "x": 191,
    "y": -1351,
    "name": "Main School Building",
    "rotation": -3,
    "width": 315,
    "length": 151,
    "clip": 50,
    "on_enter": 11
  },
  {
    "id": 38,
    "shape": "rect",
    "x": 417,
    "y": 9,
    "name": "Main School Building",
    "rotation": -1,
    "width": 667,
    "length": 360,
    "clip": 50,
    "on_enter": 11
  },
  {
    "id": 39,
    "shape": "rect",
    "x": -881,
    "y": -1330,
    "name": "Main School Building",
    "rotation": -3,
    "width": 195,
    "length": 262,
    "clip": 50,
    "on_enter": 11
  },
  {
    "id": 41,
    "shape": "rect",
    "x": -560,
    "y": -853,
    "name": "Main School Building",
    "rotation": -45,
    "width": 211,
    "length": 73,
    "clip": 50,
    "on_enter": 11
  },
  {
    "id": 42,
    "shape": "rect",
    "x": -670,
    "y": -783,
    "name": "Main School Building",
    "rotation": -2,
    "width": 147,
    "length": 62,
    "clip": 50,
    "on_enter": 11
  },
  {
    "id": 43,
    "shape": "rect",
    "x": -65,
    "y": -277,
    "name": "Main School Building",
    "rotation": -2,
    "width": 145,
    "length": 215,
    "clip": 50,
    "on_enter": 11
  }
]